odoo9_addon_l10n_lu_mis_reports-9.0.1.0.0.99.dev11-py2.7-nspkg.pth
odoo9_addon_l10n_lu_mis_reports-9.0.1.0.0.99.dev11.dist-info/METADATA
odoo9_addon_l10n_lu_mis_reports-9.0.1.0.0.99.dev11.dist-info/RECORD
odoo9_addon_l10n_lu_mis_reports-9.0.1.0.0.99.dev11.dist-info/WHEEL
odoo9_addon_l10n_lu_mis_reports-9.0.1.0.0.99.dev11.dist-info/namespace_packages.txt
odoo9_addon_l10n_lu_mis_reports-9.0.1.0.0.99.dev11.dist-info/top_level.txt
odoo_addons/l10n_lu_mis_reports/README.rst
odoo_addons/l10n_lu_mis_reports/__init__.py
odoo_addons/l10n_lu_mis_reports/__openerp__.py
odoo_addons/l10n_lu_mis_reports/data/mis_report_abr_bs.xml
odoo_addons/l10n_lu_mis_reports/data/mis_report_abr_pl.xml
odoo_addons/l10n_lu_mis_reports/data/mis_report_bs.xml
odoo_addons/l10n_lu_mis_reports/data/mis_report_ca.xml
odoo_addons/l10n_lu_mis_reports/data/mis_report_pl.xml
odoo_addons/l10n_lu_mis_reports/data/mis_report_styles.xml
odoo_addons/l10n_lu_mis_reports/i18n/l10n_lu_mis_reports.pot
odoo_addons/l10n_lu_mis_reports/static/description/icon.png
