Metadata-Version: 2.1
Name: odoo9-addon-l10n-lu-mis-reports
Version: 9.0.1.0.0.99.dev11
Summary: MIS Report templates for the Luxembourg P&L and Balance Sheets
Home-page: http://acsone.eu
Author: ACSONE SA/NV,Odoo Community Association (OCA)
Author-email: support@odoo-community.org
License: AGPL-3
Platform: UNKNOWN
Classifier: Programming Language :: Python
Classifier: Framework :: Odoo
Classifier: License :: OSI Approved :: GNU Affero General Public License v3
Requires-Python: ~=2.7
Requires-Dist: odoo9-addon-mis-builder
Requires-Dist: odoo (<9.1a,>=9.0a)
